LICENSE
README.md
setup.py
bin/qmrun-orca6
bin/qmrun-orca6-stdout
bin/qmrun-orca6.ps1
qmrun/__init__.py
qmrun/qmdriver.py
qmrun/qmparser.py
qmrun/qmwriter.py
qmrun.egg-info/PKG-INFO
qmrun.egg-info/SOURCES.txt
qmrun.egg-info/dependency_links.txt
qmrun.egg-info/entry_points.txt
qmrun.egg-info/requires.txt
qmrun.egg-info/top_level.txt