Metadata-Version: 2.4
Name: qmrun
Version: 0.1.4
Summary: Orca6 input file generator from SDF files
Home-page: https://github.com/NMRDev/qmrun
Author: Armando Navarro-Vázquez
Author-email: armando.navarro@ufpe.br
License: MIT
Classifier: Development Status :: 1 - Planning
Classifier: Intended Audience :: Science/Research
Classifier: Programming Language :: Python :: 3
License-File: LICENSE
Requires-Dist: rdkit
Dynamic: author
Dynamic: author-email
Dynamic: classifier
Dynamic: description
Dynamic: description-content-type
Dynamic: home-page
Dynamic: license
Dynamic: license-file
Dynamic: requires-dist
Dynamic: summary
